pr_properties/__init__.py
pr_properties/pr_properties.py
pr_properties/test_case/__init__.py
pr_properties/test_case/pool.properties
pr_properties/test_case/pool.properties.bak
pr_properties/test_case/pool.properties.pr_bak
pr_properties/test_case/test_properties.py
pr_properties-1.8.7.dist-info/METADATA
pr_properties-1.8.7.dist-info/WHEEL
pr_properties-1.8.7.dist-info/licenses/LICENSE
pr_properties-1.8.7.dist-info/licenses/license.txt
pr_properties-1.8.7.dist-info/RECORD
