Metadata-Version: 2.4
Name: pr_properties
Version: 1.8.7
Summary: A Python library for reading, writing and managing .properties configuration files with file lock support.
Project-URL: Homepage, https://gitee.com/FrancizTest_admin/pr_properties
Project-URL: Source, https://gitee.com/FrancizTest_admin/pr_properties
Project-URL: Issues, https://gitee.com/FrancizTest_admin/pr_properties/issues
Author-email: Franciz <Franciz467@163.com>
License: Apache-2.0
License-File: LICENSE
License-File: license.txt
Keywords: config,configuration,filelock,parser,properties
Classifier: Development Status :: 5 - Production/Stable
Classifier: License :: OSI Approved :: Apache Software License
Classifier: Operating System :: OS Independent
Classifier: Programming Language :: Python :: 3
Classifier: Programming Language :: Python :: 3.7
Classifier: Programming Language :: Python :: 3.8
Classifier: Programming Language :: Python :: 3.9
Classifier: Programming Language :: Python :: 3.10
Classifier: Programming Language :: Python :: 3.11
Requires-Python: >=3.7
Requires-Dist: filelock<4.0.0,>=3.12.2
